dubious/GuildStructure.py
dubious/Interaction.py
dubious/Machines.py
dubious/Pory.py
dubious/Pory2.py
dubious/Pory_Z.py
dubious/Register.py
dubious/__init__.py
dubious/discord/__init__.py
dubious/discord/api.py
dubious/discord/core.py
dubious/discord/enums.py
dubious/discord/make.py
dubious/discord/rest.py
dubiousdiscord-0.5.3.dist-info/LICENSE
dubiousdiscord-0.5.3.dist-info/METADATA
dubiousdiscord-0.5.3.dist-info/WHEEL
dubiousdiscord-0.5.3.dist-info/top_level.txt
dubiousdiscord-0.5.3.dist-info/RECORD
